Pbaysalt/__init__.py
Pbaysalt-0.0.1.dist-info/METADATA
Pbaysalt-0.0.1.dist-info/WHEEL
Pbaysalt-0.0.1.dist-info/top_level.txt
Pbaysalt-0.0.1.dist-info/RECORD
