Metadata-Version: 2.1
Name: Pbaysalt
Version: 0.0.1
Summary: Some simple tools for Christmas
Author: Christmas
Author-email: 273519355@qq.com
Classifier: Programming Language :: Python :: 3
Classifier: License :: OSI Approved :: MIT License
Classifier: Operating System :: OS Independent
Requires-Python: >=3.6
